grader_helper/__init__.py
grader_helper/dependencies.py
grader_helper/assignment/__init__.py
grader_helper/assignment/assign_graders_groups.py
grader_helper/assignment/assign_graders_individual.py
grader_helper/assignment/find_unsubmitted.py
grader_helper/assignment/visualise.py
grader_helper/dataframe_operations/__init__.py
grader_helper/dataframe_operations/calculate_total_module_score.py
grader_helper/dataframe_operations/calculate_weighted_score.py
grader_helper/dataframe_operations/check_for_weighted_columns.py
grader_helper/dataframe_operations/make_letter_grade.py
grader_helper/dataframe_operations/prepare_data_for_departmental_template.py
grader_helper/dataframe_operations/sort_order_columns.py
grader_helper/file_operations/__init__.py
grader_helper/file_operations/alphabetise_folders.py
grader_helper/file_operations/brightspace_name_folders.py
grader_helper/file_operations/catch_grades.py
grader_helper/file_operations/distribute_feedback_sheets.py
grader_helper/file_operations/extract_studentid_grade.py
grader_helper/file_operations/save_distributed_graders.py
grader_helper/file_operations/save_grader_sheets.py
grader_helper/file_operations/scan_multiple_submissions.py
grader_helper/ingesting/__init__.py
grader_helper/ingesting/import_brightspace_classlist.py
grader_helper/ingesting/ingest_completed_graderfiles.py
grader_helper/ingesting/load_graders.py
grader_helper-0.1.13.dist-info/METADATA
grader_helper-0.1.13.dist-info/WHEEL
grader_helper-0.1.13.dist-info/RECORD
