Metadata-Version: 2.4
Name: grader-helper
Version: 0.1.13
Summary: Functions to help manage assignments from UL which are hosted on Brightspace
Author-email: Kevin O Malley <kevomalley743@gmail.com>
License-Expression: MIT
Requires-Python: >=3.13
Requires-Dist: matplotlib<3.10,>=3.9
Requires-Dist: numpy>=2.2.1
Requires-Dist: openpyxl>=3.1.5
Requires-Dist: pandas>=2.2.3
Requires-Dist: python-calamine>=0.4.0
Requires-Dist: tqdm>=4.67.1
Requires-Dist: xlwings>=0.33.5
